lib_registry/__init__.py
lib_registry/__init__conf__.py
lib_registry/helpers.py
lib_registry/lib_registry.py
lib_registry/lib_registry_cli.py
lib_registry/py.typed
lib_registry/types_custom.py
lib_registry-2.0.10.dist-info/LICENSE
lib_registry-2.0.10.dist-info/METADATA
lib_registry-2.0.10.dist-info/WHEEL
lib_registry-2.0.10.dist-info/entry_points.txt
lib_registry-2.0.10.dist-info/top_level.txt
lib_registry-2.0.10.dist-info/RECORD
