Metadata-Version: 2.1
Name: lib_registry
Version: 2.0.10
Summary: a more pythonic way to access the windows registry as winreg
Author-email: Robert Nowotny <bitranox@gmail.com>
License: MIT
Project-URL: Homepage, https://github.com/bitranox/lib_registry
Project-URL: Documentation, https://github.com/bitranox/lib_registry/blob/master/README.rst
Project-URL: Repository, https://github.com/bitranox/lib_registry.git
Project-URL: Changelog, https://github.com/bitranox/lib_registry/blob/master/CHANGES.rst
Classifier: Development Status :: 5 - Production/Stable
Classifier: Intended Audience :: Developers
Classifier: License :: OSI Approved :: MIT License
Classifier: Natural Language :: English
Classifier: Operating System :: OS Independent
Classifier: Programming Language :: Python
Classifier: Topic :: Software Development :: Libraries :: Python Modules
Requires-Python: >=3.8.0
Provides-Extra: test
License-File: LICENSE
